COPYING
MANIFEST.in
README.rst
buildout.cfg
develop.cfg
requirements.txt
setup.py
version.txt
bob/__init__.py
bob.db.casme2.egg-info/PKG-INFO
bob.db.casme2.egg-info/SOURCES.txt
bob.db.casme2.egg-info/dependency_links.txt
bob.db.casme2.egg-info/entry_points.txt
bob.db.casme2.egg-info/not-zip-safe
bob.db.casme2.egg-info/requires.txt
bob.db.casme2.egg-info/top_level.txt
bob/db/__init__.py
bob/db/casme2/__init__.py
bob/db/casme2/create.py
bob/db/casme2/driver.py
bob/db/casme2/models.py
bob/db/casme2/query.py
bob/db/casme2/test.py
bob/db/casme2/version.py
doc/conf.py
doc/guide.rst
doc/index.rst
doc/py_api.rst