Metadata-Version: 1.1
Name: bob.db.casme2
Version: 2.1.6
Summary: CASME2  Database Access API for Bob
Home-page: https://gitlab.idiap.ch/bob/bob.db.casme2
Author: Abdullahi Adamu
Author-email: research.abdullah@gmail.com
License: GPLv3
Keywords: micro-expressions,bob,bob.db,CASME2
Platform: UNKNOWN
Classifier: Framework :: Bob
Classifier: Development Status :: 4 - Beta
Classifier: Environment :: Console
Classifier: Intended Audience :: Developers
Classifier: Intended Audience :: Education
Classifier: Intended Audience :: Science/Research
Classifier: License :: OSI Approved :: GNU General Public License v3 (GPLv3)
Classifier: Natural Language :: English
Classifier: Programming Language :: Python
Classifier: Programming Language :: Python :: 2.7
Classifier: Topic :: Scientific/Engineering :: Artificial Intelligence
Classifier: Topic :: Database :: Front-Ends
